my_model/VERSION
my_model/__init__.py
my_model/config.yml
my_model/pec2_pipeline.py
my_model/pec2_pipeline_train.py
my_model/pec2_predict.py
my_model/config/__init__.py
my_model/config/core.py
my_model/datasets/__init__.py
my_model/datasets/titanic.csv
my_model/processing/__init__.py
my_model/processing/data_manager.py
my_model/processing/validation.py
my_model/trained_models/__init__.py
my_model/trained_models/titanic_pipeline_m0.0.3.pkl
xabier_burgos_AE_PEC2_xburgos-0.0.3.dist-info/METADATA
xabier_burgos_AE_PEC2_xburgos-0.0.3.dist-info/WHEEL
xabier_burgos_AE_PEC2_xburgos-0.0.3.dist-info/top_level.txt
xabier_burgos_AE_PEC2_xburgos-0.0.3.dist-info/RECORD
